MANIFEST.in
README.md
pyproject.toml
requirements.txt
setup.py
video_cli/__init__.py
video_cli.egg-info/PKG-INFO
video_cli.egg-info/SOURCES.txt
video_cli.egg-info/dependency_links.txt
video_cli.egg-info/entry_points.txt
video_cli.egg-info/requires.txt
video_cli.egg-info/top_level.txt
video_cli/cli/__init__.py
video_cli/cli/crop.py
video_cli/cli/fromimg.py
video_cli/cli/metadata.py
video_cli/cli/resize.py
video_cli/cli/retime.py
video_cli/cli/tile.py
video_cli/cli/togif.py
video_cli/cli/toimg.py
video_cli/cli/tovideo.py
video_cli/cli/trim.py
video_cli/utils/__init__.py
video_cli/utils/get_macro_block_size.py
video_cli/utils/natural_sort.py
video_cli/utils/resize_to_even.py